j_vault_http_client_xethhung12/JVaultHttpClient.py
j_vault_http_client_xethhung12/__init__.py
j_vault_http_client_xethhung12-0.1.1.dist-info/METADATA
j_vault_http_client_xethhung12-0.1.1.dist-info/WHEEL
j_vault_http_client_xethhung12-0.1.1.dist-info/licenses/LICENSE
j_vault_http_client_xethhung12-0.1.1.dist-info/RECORD
